congress/__init__.py
congress/run.py
congress/contrib/__init__.py
congress/contrib/beanstalkd.py
congress/tasks/__init__.py
congress/tasks/adler_wilkerson_bills.py
congress/tasks/amendment_info.py
congress/tasks/bill_info.py
congress/tasks/bills.py
congress/tasks/committee_meetings.py
congress/tasks/govinfo.py
congress/tasks/nomination_info.py
congress/tasks/nominations.py
congress/tasks/statutes.py
congress/tasks/upcoming_house_floor.py
congress/tasks/utils.py
congress/tasks/vote_info.py
congress/tasks/votes.py
congress/tasks/voteview.py
pb_congress_scraper-0.0.8.data/scripts/bills.sh
pb_congress_scraper-0.0.8.data/scripts/statutes.sh
pb_congress_scraper-0.0.8.data/scripts/votes.sh
pb_congress_scraper-0.0.8.data/scripts/voteview.sh
pb_congress_scraper-0.0.8.dist-info/LICENSE
pb_congress_scraper-0.0.8.dist-info/METADATA
pb_congress_scraper-0.0.8.dist-info/WHEEL
pb_congress_scraper-0.0.8.dist-info/entry_points.txt
pb_congress_scraper-0.0.8.dist-info/top_level.txt
pb_congress_scraper-0.0.8.dist-info/RECORD
