Metadata-Version: 2.1
Name: pb-congress-scraper
Version: 0.0.8
Summary: Public domain data collectors for the work of Congress, including legislation, amendments, and votes.
Author: The unitedstates organization on GitHub
License: CC0-1.0
License-File: LICENSE
Requires-Dist: beautifulsoup4
Requires-Dist: cssselect
Requires-Dist: iso8601
Requires-Dist: lxml
Requires-Dist: mechanize
Requires-Dist: mock
Requires-Dist: rtyaml
Requires-Dist: python-dateutil
Requires-Dist: pytz
Requires-Dist: pyyaml
Requires-Dist: scrapelib
Requires-Dist: xmltodict
Requires-Dist: packaging
